hetrob/__init__.py
hetrob/_testing.py
hetrob/cli.py
hetrob/hetrob.py
hetrob/pledge.py
hetrob/problem.py
hetrob/result.py
hetrob/run.py
hetrob/search.py
hetrob/solution.py
hetrob/util.py
hetrob/visualization.py
hetrob/annealing/__init__.py
hetrob/annealing/improvement.py
hetrob/annealing/search.py
hetrob/annealing/solve.py
hetrob/annealing/temperature.py
hetrob/data/__init__.py
hetrob/data/_set.py
hetrob/data/arches/arches_lite_large_1.json
hetrob/data/hsvrsp_variable_coop/hsvrsp_n_100_m_10_ncoop_1.json
hetrob/data/hsvrsp_variable_coop/hsvrsp_n_100_m_10_ncoop_10.json
hetrob/data/hsvrsp_variable_coop/hsvrsp_n_100_m_10_ncoop_11.json
hetrob/data/hsvrsp_variable_coop/hsvrsp_n_100_m_10_ncoop_12.json
hetrob/data/hsvrsp_variable_coop/hsvrsp_n_100_m_10_ncoop_13.json
hetrob/data/hsvrsp_variable_coop/hsvrsp_n_100_m_10_ncoop_14.json
hetrob/data/hsvrsp_variable_coop/hsvrsp_n_100_m_10_ncoop_15.json
hetrob/data/hsvrsp_variable_coop/hsvrsp_n_100_m_10_ncoop_16.json
hetrob/data/hsvrsp_variable_coop/hsvrsp_n_100_m_10_ncoop_17.json
hetrob/data/hsvrsp_variable_coop/hsvrsp_n_100_m_10_ncoop_18.json
hetrob/data/hsvrsp_variable_coop/hsvrsp_n_100_m_10_ncoop_19.json
hetrob/data/hsvrsp_variable_coop/hsvrsp_n_100_m_10_ncoop_2.json
hetrob/data/hsvrsp_variable_coop/hsvrsp_n_100_m_10_ncoop_20.json
hetrob/data/hsvrsp_variable_coop/hsvrsp_n_100_m_10_ncoop_3.json
hetrob/data/hsvrsp_variable_coop/hsvrsp_n_100_m_10_ncoop_4.json
hetrob/data/hsvrsp_variable_coop/hsvrsp_n_100_m_10_ncoop_5.json
hetrob/data/hsvrsp_variable_coop/hsvrsp_n_100_m_10_ncoop_6.json
hetrob/data/hsvrsp_variable_coop/hsvrsp_n_100_m_10_ncoop_7.json
hetrob/data/hsvrsp_variable_coop/hsvrsp_n_100_m_10_ncoop_8.json
hetrob/data/hsvrsp_variable_coop/hsvrsp_n_100_m_10_ncoop_9.json
hetrob/data/hsvrsp_variable_heterogeneity/hsvrsp_n_100_m_10_s_1.json
hetrob/data/hsvrsp_variable_heterogeneity/hsvrsp_n_100_m_10_s_10.json
hetrob/data/hsvrsp_variable_heterogeneity/hsvrsp_n_100_m_10_s_11.json
hetrob-0.3.0.dist-info/AUTHORS.rst
hetrob-0.3.0.dist-info/LICENSE
hetrob-0.3.0.dist-info/METADATA
hetrob-0.3.0.dist-info/WHEEL
hetrob-0.3.0.dist-info/entry_points.txt
hetrob-0.3.0.dist-info/top_level.txt
hetrob-0.3.0.dist-info/RECORD
