Metadata-Version: 2.1
Name: hetrob
Version: 0.3.0
Summary: A python package for the optimzation of schedules for heterogeneous, cooperating robot teams
Home-page: https://github.com/the16thpythonist/hetrob
Author: Jonas Teufel
Author-email: jonseb1998@gmail.com
License: MIT license
Keywords: hetrob
Platform: UNKNOWN
Classifier: Development Status :: 2 - Pre-Alpha
Classifier: Intended Audience :: Developers
Classifier: License :: OSI Approved :: MIT License
Classifier: Natural Language :: English
Classifier: Programming Language :: Python :: 3
Classifier: Programming Language :: Python :: 3.5
Classifier: Programming Language :: Python :: 3.6
Classifier: Programming Language :: Python :: 3.7
Classifier: Programming Language :: Python :: 3.8
Requires-Python: >=3.5
Requires-Dist: Click (>=7.0)
Requires-Dist: deap (>=1.3.1)
Requires-Dist: matplotlib (>=3.1.2)
Requires-Dist: numpy (>=1.19.0)
Requires-Dist: psutil (>=5.7.2)
